pulumi_aiven/__init__.py
pulumi_aiven/_inputs.py
pulumi_aiven/_utilities.py
pulumi_aiven/account.py
pulumi_aiven/account_authentication.py
pulumi_aiven/account_team.py
pulumi_aiven/account_team_member.py
pulumi_aiven/account_team_project.py
pulumi_aiven/alloydbomni.py
pulumi_aiven/alloydbomni_database.py
pulumi_aiven/alloydbomni_user.py
pulumi_aiven/aws_org_vpc_peering_connection.py
pulumi_aiven/aws_privatelink.py
pulumi_aiven/aws_vpc_peering_connection.py
pulumi_aiven/azure_org_vpc_peering_connection.py
pulumi_aiven/azure_privatelink.py
pulumi_aiven/azure_privatelink_connection_approval.py
pulumi_aiven/azure_vpc_peering_connection.py
pulumi_aiven/billing_group.py
pulumi_aiven/cassandra.py
pulumi_aiven/cassandra_user.py
pulumi_aiven/clickhouse.py
pulumi_aiven/clickhouse_database.py
pulumi_aiven/clickhouse_grant.py
pulumi_aiven/clickhouse_role.py
pulumi_aiven/clickhouse_user.py
pulumi_aiven/connection_pool.py
pulumi_aiven/dragonfly.py
pulumi_aiven/flink.py
pulumi_aiven/flink_application.py
pulumi_aiven/flink_application_deployment.py
pulumi_aiven/flink_application_version.py
pulumi_aiven/flink_jar_application.py
pulumi_aiven/flink_jar_application_deployment.py
pulumi_aiven/flink_jar_application_version.py
pulumi_aiven/gcp_org_vpc_peering_connection.py
pulumi_aiven/gcp_privatelink.py
pulumi_aiven/gcp_privatelink_connection_approval.py
pulumi_aiven/gcp_vpc_peering_connection.py
pulumi_aiven/get_account.py
pulumi_aiven/get_account_authentication.py
pulumi_aiven/get_account_team.py
pulumi_aiven/get_account_team_member.py
pulumi_aiven/get_account_team_project.py
pulumi_aiven/get_alloydbomni.py
pulumi_aiven/get_alloydbomni_database.py
pulumi_aiven/get_alloydbomni_user.py
pulumi_aiven/get_aws_org_vpc_peering_connection.py
pulumi_aiven/get_aws_privatelink.py
pulumi_aiven/get_aws_vpc_peering_connection.py
pulumi_aiven/get_azure_org_vpc_peering_connection.py
pulumi_aiven/get_azure_privatelink.py
pulumi_aiven/get_azure_vpc_peering_connection.py
pulumi_aiven-6.45.0.dist-info/METADATA
pulumi_aiven-6.45.0.dist-info/WHEEL
pulumi_aiven-6.45.0.dist-info/top_level.txt
pulumi_aiven-6.45.0.dist-info/RECORD
